net_sniffer/__init__.py
net_sniffer/app.py
net_sniffer/modules/decoder.py
net_sniffer/modules/sniffer.py
net_sniffer/output/base.py
net_sniffer/output/screen.py
net_sniffer-3.1.2.dist-info/LICENSE
net_sniffer-3.1.2.dist-info/WHEEL
net_sniffer-3.1.2.dist-info/METADATA
net_sniffer-3.1.2.dist-info/RECORD
