Metadata-Version: 2.1
Name: net-sniffer
Version: 3.1.2
Summary: A Network Packet Sniffing tool developed in Python 3
Home-page: https://github.com/EONRaider/Packet-Sniffer
Author: EONRaider
Author-email: livewire_voodoo@protonmail.com
Requires-Python: >=3.8,<3.11
Classifier: Programming Language :: Python :: 3
Classifier: Programming Language :: Python :: 3.10
Classifier: Programming Language :: Python :: 3.8
Classifier: Programming Language :: Python :: 3.9
Requires-Dist: netprotocols (>=0.8.0,<0.9.0)
Project-URL: Repository, https://github.com/EONRaider/Packet-Sniffer
